CHANGELOG.txt
LICENCE.txt
MANIFEST.in
README.txt
setup.py
algorsort/__init__.py
algorsort.egg-info/PKG-INFO
algorsort.egg-info/SOURCES.txt
algorsort.egg-info/dependency_links.txt
algorsort.egg-info/top_level.txt