Metadata-Version: 1.1
Name: algorsort
Version: 2
Summary: A few sorting algorithms!
Home-page: https://jased.xyz/
Author: Jase Williams
Author-email: jased@jased.xyz
License: MIT
Keywords: sorting
Platform: UNKNOWN
Classifier: Development Status :: 5 - Production/Stable
Classifier: Intended Audience :: Developers
Classifier: Operating System :: Microsoft :: Windows :: Windows 10
Classifier: License :: OSI Approved :: MIT License
Classifier: Programming Language :: Python :: 3
